remat_data/__init__.py
remat_data/_version.py
remat_data/_version.pyi
remat_data/config.py
remat_data/dataset.py
remat_data/py.typed
remat_data-1.1.2.dist-info/METADATA
remat_data-1.1.2.dist-info/WHEEL
remat_data-1.1.2.dist-info/entry_points.txt
remat_data-1.1.2.dist-info/licenses/LICENSE
remat_data-1.1.2.dist-info/RECORD
