Metadata-Version: 2.4
Name: remat-data
Version: 1.1.2
Summary: Download datasets from the RE-MAT Clowder
Project-URL: Homepage, https://github.com/re-mat/remat-data-downloader
Project-URL: Bug Tracker, https://github.com/re-mat/remat-data-downloader/issues
Project-URL: Discussions, https://github.com/re-mat/remat-data-downloader/discussions
Project-URL: Changelog, https://github.com/re-mat/remat-data-downloader/releases
Author-email: Ben Galewsky <bengal1@illinois.edu>
License: BSD 3-Clause License
License-File: LICENSE
Classifier: Development Status :: 1 - Planning
Classifier: Intended Audience :: Developers
Classifier: Intended Audience :: Science/Research
Classifier: License :: OSI Approved :: BSD License
Classifier: Operating System :: OS Independent
Classifier: Programming Language :: Python
Classifier: Programming Language :: Python :: 3
Classifier: Programming Language :: Python :: 3 :: Only
Classifier: Programming Language :: Python :: 3.8
Classifier: Programming Language :: Python :: 3.9
Classifier: Programming Language :: Python :: 3.10
Classifier: Programming Language :: Python :: 3.11
Classifier: Programming Language :: Python :: 3.12
Classifier: Programming Language :: Python :: 3.13
Classifier: Topic :: Scientific/Engineering
Classifier: Typing :: Typed
Requires-Python: >=3.8
Requires-Dist: chardet==3.0.4
Requires-Dist: pyclowder==2.7.0
Requires-Dist: rich==13.8.1
Requires-Dist: six==1.16.0
Requires-Dist: typer==0.12.5
Requires-Dist: urllib3==1.26.17
Provides-Extra: dev
Requires-Dist: pytest-cov>=3; extra == 'dev'
Requires-Dist: pytest>=6; extra == 'dev'
Provides-Extra: docs
Requires-Dist: furo>=2023.08.17; extra == 'docs'
Requires-Dist: myst-parser>=0.13; extra == 'docs'
Requires-Dist: sphinx-autodoc-typehints; extra == 'docs'
Requires-Dist: sphinx-copybutton; extra == 'docs'
Requires-Dist: sphinx>=7.0; extra == 'docs'
Provides-Extra: test
Requires-Dist: pytest-cov>=3; extra == 'test'
Requires-Dist: pytest>=6; extra == 'test'
